tests/__init__.py
tests/tests_topsis.py
topsis/__init__.py
topsis/topsis.py
UCS_654_thapar_topsis_shrey_102103354-0.2.0.dist-info/METADATA
UCS_654_thapar_topsis_shrey_102103354-0.2.0.dist-info/WHEEL
UCS_654_thapar_topsis_shrey_102103354-0.2.0.dist-info/entry_points.txt
UCS_654_thapar_topsis_shrey_102103354-0.2.0.dist-info/top_level.txt
UCS_654_thapar_topsis_shrey_102103354-0.2.0.dist-info/RECORD
